README.md
setup.py
mst_autoattend/__init__.py
mst_autoattend/credentials.py
mst_autoattend/pretty_printer.py
mst_autoattend/wait_and_find.py
mst_autoattend.egg-info/PKG-INFO
mst_autoattend.egg-info/SOURCES.txt
mst_autoattend.egg-info/dependency_links.txt
mst_autoattend.egg-info/entry_points.txt
mst_autoattend.egg-info/requires.txt
mst_autoattend.egg-info/top_level.txt