Metadata-Version: 2.1
Name: mst-autoattend
Version: 0.12
Summary: A tool to attend the MS Team meetings for you!
Home-page: https://github.com/thealphadollar/MS-Teams-Class-Attender
Author: Shivam Kumar Jha
Author-email: coffee@thealphadollar.me
License: UNKNOWN
Platform: UNKNOWN
